rdetoolkit-1.4.3.dist-info/METADATA
rdetoolkit-1.4.3.dist-info/WHEEL
rdetoolkit-1.4.3.dist-info/entry_points.txt
rdetoolkit-1.4.3.dist-info/licenses/LICENSE
rdetoolkit/__init__.py
rdetoolkit/__init__.pyi
rdetoolkit/__main__.py
rdetoolkit/__main__.pyi
rdetoolkit/artifact/__init__.py
rdetoolkit/artifact/__init__.pyi
rdetoolkit/artifact/report.py
rdetoolkit/artifact/report.pyi
rdetoolkit/cli.py
rdetoolkit/cli.pyi
rdetoolkit/cmd/__init__.py
rdetoolkit/cmd/__init__.pyi
rdetoolkit/cmd/archive.py
rdetoolkit/cmd/archive.pyi
rdetoolkit/cmd/command.py
rdetoolkit/cmd/command.pyi
rdetoolkit/cmd/csv2graph.py
rdetoolkit/cmd/csv2graph.pyi
rdetoolkit/cmd/default.py
rdetoolkit/cmd/default.pyi
rdetoolkit/cmd/gen_config.py
rdetoolkit/cmd/gen_config.pyi
rdetoolkit/cmd/gen_excelinvoice.py
rdetoolkit/cmd/gen_excelinvoice.pyi
rdetoolkit/config.py
rdetoolkit/config.pyi
rdetoolkit/core.cpython-312-powerpc64le-linux-gnu.so
rdetoolkit/core.pyi
rdetoolkit/errors.py
rdetoolkit/errors.pyi
rdetoolkit/exceptions.py
rdetoolkit/exceptions.pyi
rdetoolkit/fileops.py
rdetoolkit/fileops.pyi
rdetoolkit/graph.pyi
rdetoolkit/graph/__init__.py
rdetoolkit/graph/__init__.pyi
rdetoolkit/graph/api.pyi
rdetoolkit/graph/api/__init__.py
rdetoolkit/graph/api/__init__.pyi
rdetoolkit/graph/api/csv2graph.py
rdetoolkit/graph/api/csv2graph.pyi
rdetoolkit/graph/config.py
rdetoolkit/graph/config.pyi
rdetoolkit/graph/exceptions.py
rdetoolkit/graph/exceptions.pyi
rdetoolkit/graph/io.pyi
rdetoolkit/graph/io/__init__.py
rdetoolkit/graph/io/__init__.pyi
rdetoolkit/graph/io/file_writer.py
rdetoolkit/graph/io/file_writer.pyi
rdetoolkit/graph/io/path_validator.py
rdetoolkit/graph/io/path_validator.pyi
rdetoolkit/graph/models.py
rdetoolkit/graph/models.pyi
rdetoolkit/graph/normalizers.py
rdetoolkit/graph/normalizers.pyi
rdetoolkit/graph/parsers.py
rdetoolkit/graph/parsers.pyi
rdetoolkit/graph/parsers/__init__.py
rdetoolkit/graph/parsers/__init__.pyi
rdetoolkit/graph/parsers/base.py
rdetoolkit/graph/parsers/base.pyi
rdetoolkit/graph/parsers/noheader_parser.py
rdetoolkit/graph/parsers/noheader_parser.pyi
rdetoolkit/graph/parsers/parser_factory.py
rdetoolkit-1.4.3.dist-info/RECORD
