Metadata-Version: 2.4
Name: rdetoolkit
Version: 1.4.3
Classifier: Development Status :: 3 - Alpha
Classifier: Programming Language :: Python
Classifier: Programming Language :: Python :: 3
Classifier: Programming Language :: Python :: 3 :: Only
Classifier: Programming Language :: Python :: 3.9
Classifier: Programming Language :: Python :: 3.10
Classifier: Programming Language :: Python :: 3.11
Classifier: Programming Language :: Python :: 3.12
Classifier: Programming Language :: Python :: 3.13
Classifier: Programming Language :: Rust
Classifier: License :: OSI Approved :: MIT License
Classifier: Operating System :: POSIX :: Linux
Classifier: Operating System :: Microsoft :: Windows
Classifier: Operating System :: MacOS
Classifier: Typing :: Typed
Requires-Dist: chardet>=5.2.0
Requires-Dist: charset-normalizer>=3.2.0
Requires-Dist: openpyxl>=3.1.2
Requires-Dist: pandas>=2.2.3
Requires-Dist: build>=1.0.3
Requires-Dist: click>=8.1.7
Requires-Dist: toml>=0.10.2
Requires-Dist: pydantic>=2.8.3
Requires-Dist: jsonschema>=4.21.1
Requires-Dist: tomlkit>=0.12.4
Requires-Dist: pyyaml>=6.0.1
Requires-Dist: eval-type-backport>=0.2.0
Requires-Dist: numpy>=1.26.4
Requires-Dist: polars>=1.9.0
Requires-Dist: pyarrow>=19.0.0
Requires-Dist: pip>=24.3.1
Requires-Dist: markdown>=3.7
Requires-Dist: types-pytz>=2025.2.0.20250326
Requires-Dist: matplotlib>=3.9.4
Requires-Dist: minio>=7.2.15 ; extra == 'minio'
Requires-Dist: plotly>=6.3.1 ; extra == 'plotly'
Provides-Extra: minio
Provides-Extra: plotly
License-File: LICENSE
Summary: A module that supports the workflow of the RDE dataset construction program
Keywords: rdetoolkit,RDE,toolkit,structure,dataset
Author-email: NIMS MDPF <rde@nims.go>
Requires-Python: >=3.9
Project-URL: Homepage, https://github.com/nims-dpfc/rdetoolkit
Project-URL: Bug Tracker, https://github.com/nims-dpfc/rdetoolkit
